{
  "_class": "symbolInstance",
  "booleanOperation": 0,
  "clippingMaskMode": 0,
  "do_objectID": "53551516-A5F8-44BC-93FA-8C7CBAA044A9",
  "exportOptions": {
    "_class": "exportOptions",
    "do_objectID": "244E935C-43A9-468A-A231-133AF171B480",
    "exportFormats": [
    ],
    "includedLayerIds": [
    ],
    "layerOptions": 0,
    "shouldTrim": false
  },
  "frame": {
    "_class": "rect",
    "constrainProportions": false,
    "do_objectID": "FBACC1B7-D211-4F68-88A1-3F57B4EDA230",
    "height": 151,
    "width": 220,
    "x": 0,
    "y": 0
  },
  "hasClippingMask": false,
  "horizontalSpacing": 0,
  "isFixedToViewport": false,
  "isFlippedHorizontal": false,
  "isFlippedVertical": false,
  "isLocked": false,
  "isVisible": true,
  "layerListExpandedType": 0,
  "name": "sidenav/side-header",
  "nameIsFixed": false,
  "overrideValues": [
  ],
  "resizingConstraint": 63,
  "resizingType": 0,
  "rotation": 0,
  "scale": 1,
  "shouldBreakMaskChain": false,
  "style": {
    "_class": "style",
    "do_objectID": "A0C47BD9-17AE-4BC9-8D3A-88C3133E2F19",
    "endMarkerType": 0,
    "miterLimit": 10,
    "startMarkerType": 0,
    "windingRule": 1
  },
  "symbolID": "C90282FC-3B7C-41EB-9D13-0E4443A03F4D",
  "userInfo": {
    "com.invisionlabs.library": {
      "original-layer": {
        "originalID": "DB520D85-BC59-4F00-B703-6FA8F2BB10A6",
        "version": 1
      }
    }
  },
  "verticalSpacing": 0
}