{
  "_class": "symbolInstance",
  "do_objectID": "BDA5879E-D4AF-4A2B-A898-4893B9D33B3D",
  "exportOptions": {
    "_class": "exportOptions",
    "do_objectID": "9FBB1AC5-5B2B-4E21-A87C-F02333954C90",
    "exportFormats": [
    ],
    "includedLayerIds": [
    ],
    "layerOptions": 0,
    "shouldTrim": false
  },
  "frame": {
    "_class": "rect",
    "constrainProportions": false,
    "do_objectID": "80C22F94-2CF8-4FC6-BBFF-89337939D72A",
    "height": 46.27165354330705,
    "width": 220.0000000000002,
    "x": 0,
    "y": 231.3582677165355
  },
  "horizontalSpacing": 0,
  "isFlippedHorizontal": false,
  "isFlippedVertical": false,
  "isLocked": false,
  "isVisible": false,
  "layerListExpandedType": 0,
  "name": "navbar/side-menu",
  "nameIsFixed": false,
  "overrideValues": [
  ],
  "overrides": {
  },
  "resizingConstraint": 63,
  "resizingType": 0,
  "rotation": 0,
  "scale": 1,
  "shouldBreakMaskChain": false,
  "style": {
    "_class": "style",
    "do_objectID": "78FE37FF-0BFF-4360-94A0-DAA476D2B9DB",
    "endDecorationType": 0,
    "miterLimit": 10,
    "startDecorationType": 0
  },
  "symbolID": "29EAC89F-8991-4CE0-9AAF-E7CF52F0FC82",
  "userInfo": {
    "com.invisionlabs.library": {
      "original-layer": {
        "originalID": "F6FAC3C2-4C1D-4E3A-9E98-5D6D2A3802D3",
        "version": 1
      }
    }
  },
  "verticalSpacing": 0
}