{
  "_class": "shapePath",
  "booleanOperation": -1,
  "do_objectID": "92667861-B2C5-47CF-8433-E75EAFA35DF5",
  "edited": true,
  "exportOptions": {
    "_class": "exportOptions",
    "do_objectID": "09ABBAB0-B224-45A8-AE33-AE0C9A73D97E",
    "exportFormats": [
    ],
    "includedLayerIds": [
    ],
    "layerOptions": 0,
    "shouldTrim": false
  },
  "frame": {
    "_class": "rect",
    "constrainProportions": false,
    "do_objectID": "A62EBE26-A208-4E83-9274-44DC3FDEA432",
    "height": 6.4412736,
    "width": 1.216853243602155,
    "x": 0,
    "y": 0
  },
  "isClosed": true,
  "isFlippedHorizontal": false,
  "isFlippedVertical": false,
  "isLocked": false,
  "isVisible": true,
  "layerListExpandedType": 0,
  "name": "Path-2-path",
  "nameIsFixed": false,
  "pointRadiusBehaviour": 1,
  "points": [
    {
      "_class": "curvePoint",
      "cornerRadius": 0,
      "curveFrom": "{0, 1}",
      "curveMode": 4,
      "curveTo": "{0, 1}",
      "hasCurveFrom": false,
      "hasCurveTo": true,
      "point": "{0, 1}"
    },
    {
      "_class": "curvePoint",
      "cornerRadius": 0,
      "curveFrom": "{0, 0}",
      "curveMode": 4,
      "curveTo": "{0, 0}",
      "hasCurveFrom": true,
      "hasCurveTo": false,
      "point": "{0, 0}"
    },
    {
      "_class": "curvePoint",
      "cornerRadius": 0,
      "curveFrom": "{0.14315943104390536, 0.77612327442429052}",
      "curveMode": 2,
      "curveTo": "{1.5035579952167215, 0.16072488260053039}",
      "hasCurveFrom": true,
      "hasCurveTo": true,
      "point": "{0.82335871313031339, 0.46842408047344786}"
    }
  ],
  "resizingConstraint": 63,
  "resizingType": 0,
  "rotation": 0,
  "shouldBreakMaskChain": false
}