{
  "_class": "text",
  "attributedString": {
    "_class": "attributedString",
    "attributes": [
      {
        "_class": "stringAttribute",
        "attributes": {
          "MSAttributedStringColorAttribute": {
            "_class": "color",
            "alpha": 1,
            "blue": 0.3515444993972778,
            "green": 0.6736825108528137,
            "red": 0.9747235178947449
          },
          "MSAttributedStringFontAttribute": {
            "_class": "fontDescriptor",
            "attributes": {
              "name": "Roboto-Bold",
              "size": 15
            }
          },
          "paragraphStyle": {
            "_class": "paragraphStyle",
            "alignment": 0,
            "allowsDefaultTighteningForTruncation": 0,
            "baseWritingDirection": 0,
            "maximumLineHeight": 20,
            "minimumLineHeight": 20,
            "paragraphSpacing": 11,
            "tabStops": [
            ],
            "tighteningFactorForTruncation": 0.05
          }
        },
        "length": 5,
        "location": 0
      }
    ],
    "string": "label"
  },
  "automaticallyDrawOnUnderlyingPath": false,
  "booleanOperation": 0,
  "clippingMaskMode": 0,
  "do_objectID": "88172983-ACAB-42F7-A77D-14FC75BC4363",
  "dontSynchroniseWithSymbol": false,
  "exportOptions": {
    "_class": "exportOptions",
    "exportFormats": [
    ],
    "includedLayerIds": [
    ],
    "layerOptions": 0,
    "shouldTrim": false
  },
  "frame": {
    "_class": "rect",
    "constrainProportions": false,
    "height": 20,
    "width": 33,
    "x": 0,
    "y": 1
  },
  "glyphBounds": "{{0, 3}, {32, 13}}",
  "hasClippingMask": false,
  "isFixedToViewport": false,
  "isFlippedHorizontal": false,
  "isFlippedVertical": false,
  "isLocked": false,
  "isVisible": true,
  "layerListExpandedType": 0,
  "lineSpacingBehaviour": 2,
  "name": "label",
  "nameIsFixed": true,
  "originalObjectID": "88172983-ACAB-42F7-A77D-14FC75BC4363",
  "resizingConstraint": 43,
  "resizingType": 1,
  "rotation": 0,
  "shouldBreakMaskChain": false,
  "style": {
    "_class": "style",
    "do_objectID": "41F8BCBF-7D1C-49CF-9440-288B911E6A8E",
    "endMarkerType": 0,
    "miterLimit": 10,
    "startMarkerType": 0,
    "textStyle": {
      "_class": "textStyle",
      "encodedAttributes": {
        "MSAttributedStringColorAttribute": {
          "_class": "color",
          "alpha": 1,
          "blue": 0.3515444993972778,
          "green": 0.6736825108528137,
          "red": 0.9747235178947449
        },
        "MSAttributedStringFontAttribute": {
          "_class": "fontDescriptor",
          "attributes": {
            "name": "Roboto-Bold",
            "size": 15
          }
        },
        "paragraphStyle": {
          "_class": "paragraphStyle",
          "alignment": 0,
          "allowsDefaultTighteningForTruncation": 0,
          "baseWritingDirection": 0,
          "maximumLineHeight": 20,
          "minimumLineHeight": 20,
          "paragraphSpacing": 11,
          "tabStops": [
          ],
          "tighteningFactorForTruncation": 0.05
        }
      },
      "verticalAlignment": 0
    },
    "windingRule": 1
  },
  "textBehaviour": 0
}